cdef_analytical/__init__.py
cdef_analytical/dummy_data.py
cdef_analytical/enums.py
cdef_analytical/logging_config.py
cdef_analytical/main.py
cdef_analytical/parquet_analyzer.py
cdef_analytical/simple_table.py
cdef_analytical/tab_test.py
cdef_analytical/table.py
cdef_analytical/table_generator.py
cdef_analytical/test_table.py
cdef_analytical/utils.py
cdef_analytical/examples/analyze_parquets.py
cdef_analytical/loaders/data_loader.py
cdef_analytical/mappings/beskst13.json
cdef_analytical/mappings/civst.json
cdef_analytical/mappings/fm_mark.json
cdef_analytical/mappings/hustype.json
cdef_analytical/mappings/icd10.json
cdef_analytical/mappings/isced.json
cdef_analytical/mappings/jobkat.json
cdef_analytical/mappings/plads.json
cdef_analytical/mappings/pre_socio.json
cdef_analytical/mappings/reg.json
cdef_analytical/mappings/scd.json
cdef_analytical/mappings/socio13.json
cdef_analytical/mappings/statsb.json
cdef_analytical/mappings/tilknyt.json
cdef_analytical-0.2.0.dist-info/METADATA
cdef_analytical-0.2.0.dist-info/WHEEL
cdef_analytical-0.2.0.dist-info/RECORD
