Metadata-Version: 2.3
Name: cdef-analytical
Version: 0.2.0
Summary: Add your description here
Author-email: Tobias Kragholm <50784887+tkragholm@users.noreply.github.com>
Requires-Python: >=3.12
Requires-Dist: chardet>=5.2.0
Requires-Dist: great-tables>=0.13.0
Requires-Dist: pandas>=2.2.3
Requires-Dist: pillow>=11.0.0
Requires-Dist: polars>=1.12.0
Requires-Dist: rich>=13.9.3
Requires-Dist: scipy>=1.14.1
Requires-Dist: selenium>=4.26.1
